README.rst
setup.py
yekit/__init__.py
yekit/kit.py
yekit.egg-info/PKG-INFO
yekit.egg-info/SOURCES.txt
yekit.egg-info/dependency_links.txt
yekit.egg-info/top_level.txt
yekit.egg-info/zip-safe