Metadata-Version: 1.1
Name: yekit
Version: 0.1.3
Summary: a useful toolkit
Home-page: http://www.xuye.site
Author: ye
Author-email: wmxy123@yeah.net
License: BSD
Keywords: tool kit
Platform: UNKNOWN
Classifier: License :: OSI Approved :: BSD License
Classifier: Programming Language :: Python :: 2.7
Classifier: Intended Audience :: Developers
Classifier: Operating System :: OS Independent
